last/__init__.py
last/alignments.py
last/contexts.py
last/lattices.py
last/scatter_reduce.py
last/semirings.py
last/weight_fns.py
last_asr-0.0.4.dist-info/LICENSE
last_asr-0.0.4.dist-info/WHEEL
last_asr-0.0.4.dist-info/METADATA
last_asr-0.0.4.dist-info/RECORD
