Metadata-Version: 2.1
Name: last-asr
Version: 0.0.4
Summary: The LAttice-based Speech Transducer (LAST) library
Keywords: speech,jax
Author: LAST authors
Requires-Python: >=3.9
Classifier: Programming Language :: Python :: 3
Classifier: Programming Language :: Python :: 3 :: Only
Classifier: License :: OSI Approved :: Apache Software License
Classifier: Intended Audience :: Science/Research
Requires-Dist: einops>=0.7.0
Requires-Dist: flax>=0.8.2
Requires-Dist: jax>=0.4.25
Requires-Dist: absl-py ; extra == "dev"
Requires-Dist: numpy ; extra == "dev"
Requires-Dist: optax ; extra == "dev"
Requires-Dist: pytest ; extra == "dev"
Requires-Dist: pytest-xdist ; extra == "dev"
Requires-Dist: pylint>=2.6.0 ; extra == "dev"
Requires-Dist: yapf ; extra == "dev"
Project-URL: homepage, https://github.com/google-research/last
Project-URL: repository, https://github.com/google-research/last
Provides-Extra: dev
